tiny_python_sdk/__init__.py
tiny_python_sdk/utils.py
tiny_python_sdk/cache/__init__.py
tiny_python_sdk/cache/file_system_cache.py
tiny_python_sdk/dingtalk/__init__.py
tiny_python_sdk/email/__init__.py
tiny_python_sdk/ffmpeg/__init__.py
tiny_python_sdk/ffmpeg/ffmpeg_capture.py
tiny_python_sdk/ffmpeg/ffmpeg_concat.py
tiny_python_sdk/ffmpeg/ffmpeg_mp4tomp3.py
tiny_python_sdk/ffmpeg/ffmpeg_prune.py
tiny_python_sdk/ffmpeg/ffmpeg_read_frames.py
tiny_python_sdk/ffmpeg/ffmpeg_record.py
tiny_python_sdk/ffmpeg/ffmpeg_utils.py
tiny_python_sdk/helper/__init__.py
tiny_python_sdk/helper/cpu.py
tiny_python_sdk/logger/__init__.py
tiny_python_sdk/logger/timerotaingfilehandler.py
tiny_python_sdk-1.0.1.dist-info/LICENSE
tiny_python_sdk-1.0.1.dist-info/METADATA
tiny_python_sdk-1.0.1.dist-info/WHEEL
tiny_python_sdk-1.0.1.dist-info/entry_points.txt
tiny_python_sdk-1.0.1.dist-info/top_level.txt
tiny_python_sdk-1.0.1.dist-info/RECORD
